itranslate/__init__.py
itranslate/atranslate.py
itranslate/itranslate.py
LICENSE
itranslate-0.1.2.dist-info/LICENSE
itranslate-0.1.2.dist-info/WHEEL
itranslate-0.1.2.dist-info/METADATA
itranslate-0.1.2.dist-info/RECORD
