Metadata-Version: 2.1
Name: itranslate
Version: 0.1.2
Summary: Google translate free and unlimited, itranslate since gtranslate is taken
Home-page: https://github.com/ffreemt/google-stranslate
License: MIT
Author: ffreemt
Requires-Python: >=3.7,<4.0
Classifier: License :: OSI Approved :: MIT License
Classifier: Programming Language :: Python :: 3
Classifier: Programming Language :: Python :: 3.7
Classifier: Programming Language :: Python :: 3.8
Classifier: Programming Language :: Python :: 3.9
Classifier: Programming Language :: Python :: 3.10
Requires-Dist: httpx (>=0.18.2,<0.19.0)
Requires-Dist: joblib (>=1.0.1,<2.0.0)
Requires-Dist: logzero (>=1.7.0,<2.0.0)
Project-URL: Repository, https://github.com/ffreemt/google-stranslate
